LICENSE.txt
MANIFEST.in
README.md
setup.cfg
setup.py
tests/__init__.py
tests/conftest.py
tests/test_backends.py
tests/test_cli_script.py
tests/test_connections.py
tests/test_internalmigrations.py
tests/test_migrations.py
tests/test_utils.py
yoyo/__init__.py
yoyo/__main__.py
yoyo/backends.py
yoyo/compat.py
yoyo/config.py
yoyo/connections.py
yoyo/exceptions.py
yoyo/migrations.py
yoyo/utils.py
yoyo/internalmigrations/__init__.py
yoyo/internalmigrations/v1.py
yoyo/internalmigrations/v2.py
yoyo/scripts/__init__.py
yoyo/scripts/main.py
yoyo/scripts/migrate.py
yoyo/scripts/newmigration.py
yoyo_database_migrations.egg-info/PKG-INFO
yoyo_database_migrations.egg-info/SOURCES.txt
yoyo_database_migrations.egg-info/dependency_links.txt
yoyo_database_migrations.egg-info/entry_points.txt
yoyo_database_migrations.egg-info/requires.txt
yoyo_database_migrations.egg-info/top_level.txt